aica_challenge_1_heuristic_agent/__init__.py
aica_challenge_1_heuristic_agent/main.py
aica_challenge_1_heuristic_agent-1.4.0.dist-info/entry_points.txt
aica_challenge_1_heuristic_agent-1.4.0.dist-info/METADATA
aica_challenge_1_heuristic_agent-1.4.0.dist-info/WHEEL
aica_challenge_1_heuristic_agent-1.4.0.dist-info/RECORD
