Metadata-Version: 2.3
Name: aica-challenge-1-heuristic-agent
Version: 1.4.0
Summary: This is a heuristic agent for AICA challenge 1
Author: Martin Drasar
Author-email: drasar@ics.muni.cz
Requires-Python: ==3.12.*
Classifier: Programming Language :: Python :: 3
Classifier: Programming Language :: Python :: 3.12
Requires-Dist: cyst-core (>=0.6.5)
Requires-Dist: py-flags (>=1.1.4,<2.0.0)
